error_mapper/__init__.py
error_mapper/protocols.py
error_mapper/py.typed
error_mapper/types.py
error_mapper/error_map/__init__.py
error_mapper/error_map/_async.py
error_mapper/error_map/_decorator.py
error_mapper/error_map/_process_error.py
error_mapper/error_map/_sync.py
error_mapper/execute/__init__.py
error_mapper/execute/_async.py
error_mapper/execute/_decorator.py
error_mapper/execute/_process_error.py
error_mapper/execute/_sync.py
error_mapper/suppress/__init__.py
error_mapper/suppress/_async.py
error_mapper/suppress/_decorator.py
error_mapper/suppress/_sync.py
error_mapper-1.0.6.dist-info/METADATA
error_mapper-1.0.6.dist-info/WHEEL
error_mapper-1.0.6.dist-info/licenses/LICENSE
error_mapper-1.0.6.dist-info/RECORD
