Metadata-Version: 2.3
Name: error-mapper
Version: 1.0.6
Summary: Decorator error mapper
Project-URL: Homepage, https://pypi.org/project/error-mapper/
Project-URL: Repository, https://github.com/likeinlife/error_mapper
Author-email: likeinlife <likeinlife@outlook.com>
License-Expression: MIT
License-File: LICENSE
Keywords: decorator,error mapping
Classifier: Intended Audience :: Developers
Classifier: License :: OSI Approved :: MIT License
Classifier: Operating System :: OS Independent
Classifier: Programming Language :: Python
Classifier: Programming Language :: Python :: 3 :: Only
Classifier: Programming Language :: Python :: 3.11
Classifier: Programming Language :: Python :: 3.12
Classifier: Programming Language :: Python :: 3.13
Classifier: Topic :: Software Development :: Libraries :: Python Modules
Requires-Python: >=3.11
